pyneid/__init__.py
pyneid/neid/__init__.py
pyneid/neid/core.py
tests/__init__.py
tests/test_queries.py
pyneid-1.0.5.dist-info/LICENSE
pyneid-1.0.5.dist-info/METADATA
pyneid-1.0.5.dist-info/WHEEL
pyneid-1.0.5.dist-info/top_level.txt
pyneid-1.0.5.dist-info/RECORD
