Metadata-Version: 2.1
Name: pyneid
Version: 1.0.5
Summary: NEID archive access client
Home-page: https://github.com/Caltech-IPAC/pyNEID
Author: Mihseh Kong
License: UNKNOWN
Platform: UNKNOWN
Classifier: Intended Audience :: Science/Research
Classifier: Programming Language :: Python :: 3.6
Classifier: Programming Language :: Python :: 3.7
Classifier: License :: OSI Approved :: MIT License
Classifier: Topic :: Scientific/Engineering :: Astronomy
Requires-Python: >= 3.6
Requires-Dist: xmltodict
Requires-Dist: lxml
Requires-Dist: bs4
Requires-Dist: requests
Requires-Dist: astropy
Requires-Dist: pytest
Requires-Dist: pytest-cov
Requires-Dist: coveralls
